src/CheckerSrtFormat.py
src/CorrectorTool.py
src/DialogScript.py
src/ErrorClass.py
src/GuiPyConcatSRT.py
src/ReaderFileSrt.py
src/SrtPyMain.py
src/WriterFileSrt.py
src/__init__.py
src/run_cli.py
src/run_gui.py
srtpy-0.1.3.dist-info/LICENSE
srtpy-0.1.3.dist-info/METADATA
srtpy-0.1.3.dist-info/WHEEL
srtpy-0.1.3.dist-info/entry_points.txt
srtpy-0.1.3.dist-info/RECORD
